Metadata-Version: 2.1
Name: etica
Version: 0.0.1
Summary: Etica 
Home-page: https://github.com/etica
Author: EticaProtocol
Author-email: info@eticaprotocol.org
License: MIT
Platform: UNKNOWN
